chart_review/__init__.py
chart_review/agree.py
chart_review/cli.py
chart_review/cli_utils.py
chart_review/cohort.py
chart_review/common.py
chart_review/config.py
chart_review/console_utils.py
chart_review/defines.py
chart_review/errors.py
chart_review/external.py
chart_review/simplify.py
chart_review/studio.py
chart_review/commands/__init__.py
chart_review/commands/accuracy.py
chart_review/commands/default.py
chart_review/commands/frequency.py
chart_review/commands/ids.py
chart_review/commands/labels.py
chart_review/commands/mcnemar.py
chart_review/commands/mentions.py
chart_review-2.4.0.dist-info/entry_points.txt
chart_review-2.4.0.dist-info/licenses/LICENSE
chart_review-2.4.0.dist-info/WHEEL
chart_review-2.4.0.dist-info/METADATA
chart_review-2.4.0.dist-info/RECORD
