Metadata-Version: 2.4
Name: chart-review
Version: 2.4.0
Summary: Medical Record Chart Review Calculator
Requires-Python: >= 3.10
License-Expression: Apache-2.0
Classifier: Operating System :: OS Independent
Classifier: Programming Language :: Python :: 3
Classifier: Topic :: Software Development :: Libraries :: Python Modules
License-File: LICENSE
Requires-Dist: ctakesclient
Requires-Dist: pyyaml >= 6
Requires-Dist: rich
Requires-Dist: scipy
Requires-Dist: pre-commit ; extra == "dev"
Requires-Dist: ruff < 0.15 ; extra == "dev"
Requires-Dist: ddt ; extra == "tests"
Requires-Dist: pytest ; extra == "tests"
Requires-Dist: pytest-cov ; extra == "tests"
Project-URL: Documentation, https://docs.smarthealthit.org/cumulus/chart-review/
Project-URL: Home, https://smarthealthit.org/cumulus/
Project-URL: Source, https://github.com/smart-on-fhir/chart-review
Provides-Extra: dev
Provides-Extra: tests
